dbtenv/__init__.py
dbtenv/execute.py
dbtenv/install.py
dbtenv/main.py
dbtenv/pip.py
dbtenv/uninstall.py
dbtenv/version.py
dbtenv/versions.py
dbtenv/which.py
dbtenv-2.2.2.dist-info/entry_points.txt
dbtenv-2.2.2.dist-info/WHEEL
dbtenv-2.2.2.dist-info/METADATA
dbtenv-2.2.2.dist-info/RECORD
